[
  {
    "name": "index___en",
    "path": "/en",
    "component": "C:\\\\Users\\\\Giovanni\\\\Desktop\\\\File\\\\Progetti\\\\www\\\\Monica Centri\\\\MonicaCentri\\\\pages\\\\index.vue",
    "chunkName": "pages/index"
  },
  {
    "name": "index___es",
    "path": "/es",
    "component": "C:\\\\Users\\\\Giovanni\\\\Desktop\\\\File\\\\Progetti\\\\www\\\\Monica Centri\\\\MonicaCentri\\\\pages\\\\index.vue",
    "chunkName": "pages/index"
  },
  {
    "name": "index___it",
    "path": "/",
    "component": "C:\\\\Users\\\\Giovanni\\\\Desktop\\\\File\\\\Progetti\\\\www\\\\Monica Centri\\\\MonicaCentri\\\\pages\\\\index.vue",
    "chunkName": "pages/index"
  }
]
